setup.py
bin/yap
yap/Env.py
yap/Location.py
yap/Makefile.py
yap/__init__.py
yap.egg-info/PKG-INFO
yap.egg-info/SOURCES.txt
yap.egg-info/dependency_links.txt
yap.egg-info/not-zip-safe
yap.egg-info/top_level.txt
yap/Generator/Generator.py
yap/Generator/Template.py
yap/Generator/__init__.py
yap/Generator/Eclipse/Android.py
yap/Generator/Eclipse/__init__.py
yap/Generator/Extensions/Qt.py
yap/Generator/Extensions/RTTI.py
yap/Generator/Extensions/__init__.py
yap/Generator/Make/Android.py
yap/Generator/Make/Flash.py
yap/Generator/Make/HTML5.py
yap/Generator/Make/Make.py
yap/Generator/Make/__init__.py
yap/Generator/VisualStudio/Windows.py
yap/Generator/VisualStudio/__init__.py
yap/Generator/VisualStudio/VCX/Configuration.py
yap/Generator/VisualStudio/VCX/Filters.py
yap/Generator/VisualStudio/VCX/Groups.py
yap/Generator/VisualStudio/VCX/ID.py
yap/Generator/VisualStudio/VCX/Project.py
yap/Generator/VisualStudio/VCX/Solution.py
yap/Generator/VisualStudio/VCX/WindowsProject.py
yap/Generator/VisualStudio/VCX/__init__.py
yap/Generator/Xcode/MacOS.py
yap/Generator/Xcode/Xcode5.py
yap/Generator/Xcode/__init__.py
yap/Generator/Xcode/iOS.py
yap/Generator/Xcode/PBX/BuildConfiguration.py
yap/Generator/Xcode/PBX/BuildPhases.py
yap/Generator/Xcode/PBX/ConfigurationList.py
yap/Generator/Xcode/PBX/Files.py
yap/Generator/Xcode/PBX/Group.py
yap/Generator/Xcode/PBX/ObjectList.py
yap/Generator/Xcode/PBX/Objects.py
yap/Generator/Xcode/PBX/Project.py
yap/Generator/Xcode/PBX/Resource.py
yap/Generator/Xcode/PBX/Targets.py
yap/Generator/Xcode/PBX/__init__.py
yap/Platform/MacOS.py
yap/Platform/Platform.py
yap/Platform/Unix.py
yap/Platform/Windows.py
yap/Platform/Xcode.py
yap/Platform/__init__.py
yap/Platform/iOS.py
yap/Target/Executable.py
yap/Target/File.py
yap/Target/Folder.py
yap/Target/Project.py
yap/Target/StaticLibrary.py
yap/Target/Target.py
yap/Target/__init__.py