Metadata-Version: 1.0
Name: yap
Version: 0.5.6
Summary: yap is a yet another project generator.
Home-page: https://github.com/dmsovetov/yap
Author: Dmitry Sovetov
Author-email: dmsovetov@gmail.com
License: MIT
Platform: UNKNOWN
